{
  "spec_hash": "2830f1e86fb1964b",
  "meta": {
    "name": "thigh180-CAP-PAA 3/5/4",
    "description": null
  },
  "stages": [
    {
      "m": 1.5,
      "b": 8.0,
      "z_sun": 18,
      "z_planet": 45,
      "z_ring": 108,
      "n_planets": 3,
      "x_sun": 0.0,
      "x_planet": 0.0,
      "x_ring": 0.0,
      "mat_sun": "PA6_CAST",
      "mat_planet": "PA6_CAST",
      "mat_ring": "PA6_ANNEAL",
      "n_planets_max": 3,
      "planet_clearance_at_max_mm": 11.339,
      "n_planets_auto": true
    },
    {
      "m": 2.5,
      "b": 8.0,
      "z_sun": 24,
      "z_planet": 21,
      "z_ring": 66,
      "n_planets": 5,
      "x_sun": 0.0,
      "x_planet": 0.0,
      "x_ring": 0.0,
      "mat_sun": "PA6_CAST",
      "mat_planet": "PA6_CAST",
      "mat_ring": "PA6_ANNEAL",
      "n_planets_max": 5,
      "planet_clearance_at_max_mm": 8.626,
      "n_planets_auto": true
    },
    {
      "m": 2.75,
      "b": 26.0,
      "z_sun": 36,
      "z_planet": 18,
      "z_ring": 72,
      "n_planets": 4,
      "x_sun": 0.0,
      "x_planet": 0.0,
      "x_ring": 0.0,
      "mat_sun": "PA6_CAST",
      "mat_planet": "PA6_CAST",
      "mat_ring": "PA6_ANNEAL",
      "n_planets_max": 6,
      "planet_clearance_at_max_mm": 19.25,
      "n_planets_auto": false
    }
  ],
  "load": {
    "mode": "output",
    "n_in": 150.0,
    "T_out_req": 180.0
  },
  "cfg": {
    "Ka": 1.3,
    "T_amb": 25.0,
    "eta_stage": 0.9,
    "n_in_ref": 150.0,
    "alpha_deg": 20.0,
    "lubrication": "grease",
    "cycles": 10000000.0
  },
  "raw": {
    "i": [
      7.0,
      3.75,
      3.0
    ],
    "i_total": 78.75,
    "n_stages": 3,
    "t_out": 180.0,
    "n_out": 1.9047619047619047,
    "T_in_equiv": 2.2857142857142856,
    "geometry": {
      "valid": true,
      "errors": [],
      "warnings": []
    },
    "model_warnings": [
      "консистентная смазка + полиамид при низком PV (мин ≈ 0.3 МПа·м/с в ст.3, <10) — смазка может НЕ снижать (для PA даже увеличивать) износ; проверить испытанием либо рассмотреть масло/сухой ход"
    ],
    "stages": [
      {
        "stage": 1,
        "i": 7.0,
        "n_planets": 3,
        "sun_torque": 2.2857142857142856,
        "sun_speed_rel": 128.57142857142858,
        "sp": {
          "SF": [
            3.3177248913418564,
            3.8886615271493588
          ],
          "SH": [
            2.1473318424943533,
            2.294069798946658
          ],
          "SigmaF": [
            19.316838634718717,
            17.343073024777663
          ],
          "SigmaH": 29.103566658335225,
          "SH_pess": 2.1473318424943533,
          "temps": {
            "flank": [
              60.08055870695207,
              39.03222348278083
            ],
            "root": [
              33.372560011392565,
              28.349024004557023
            ]
          },
          "wear": {
            "NL_ref": 1000000.0,
            "W_mean_mm": [
              0.003436453670258498,
              0.0032033427519112625
            ],
            "W_limit_mm": 0.30000000000000004,
            "N_to_limit": [
              87299300.03026445,
              93652170.00928363
            ],
            "kw_mm3_per_Nm": 1.5e-06,
            "Hv": 0.17239380711786637
          },
          "mats": [
            "PA6_CAST",
            "PA6_CAST"
          ]
        },
        "pr": {
          "force_n": 56.43738977072311,
          "d_planet": 67.5,
          "d_ring": 162.0,
          "sigma_p": 20.22222222222222,
          "sigma_r": 15.684373897707228,
          "sigma_lim_p": 34.61730288808557,
          "sigma_lim_r": 19,
          "sf_p": 3.4236892966238477,
          "sf_r": 2.422793555409624,
          "sigma_h": 12.97262750983368,
          "sigma_h_lim_p": 68.26429762155193,
          "sigma_h_lim_r": 29,
          "sh_p": 5.262179737281853,
          "sh_r": 2.235476196168975,
          "r_eq": 19.78830829241369,
          "temp_flank": {
            "planet": 28.132134898659793,
            "ring": 26.305056207774914
          },
          "temp_root": {
            "planet": 25.74753619581347,
            "ring": 25.31147341492228
          },
          "Pvzp_W": 0.047271462195824406,
          "CoF": 0.12
        },
        "deflection": {
          "lambda_sun_planet_mm": 0.052910052910052914,
          "lambda_planet_ring_mm": 0.0575785869903517,
          "limit_mm": 0.10500000000000001,
          "ok": true
        },
        "b_over_m": 5.333333333333333
      },
      {
        "stage": 2,
        "i": 3.75,
        "n_planets": 5,
        "sun_torque": 16.0,
        "sun_speed_rel": 15.714285714285714,
        "sp": {
          "SF": [
            3.085458509596071,
            2.992166098630616
          ],
          "SH": [
            1.9203483940494817,
            1.8953047321058887
          ],
          "SigmaF": [
            21.19579028876459,
            21.65472136089326
          ],
          "SigmaH": 33.53599906440437,
          "SH_pess": 1.8953047321058887,
          "temps": {
            "flank": [
              51.75624902547193,
              55.57857031482506
            ],
            "root": [
              31.385824767412636,
              32.29808544847158
            ]
          },
          "wear": {
            "NL_ref": 1000000.0,
            "W_mean_mm": [
              0.006906615625729198,
              0.0069944255225035225
            ],
            "W_limit_mm": 0.5,
            "N_to_limit": [
              72394357.39515476,
              71485499.18664864
            ],
            "kw_mm3_per_Nm": 1.5e-06,
            "Hv": 0.18836910494252532
          },
          "mats": [
            "PA6_CAST",
            "PA6_CAST"
          ]
        },
        "pr": {
          "force_n": 106.66666666666667,
          "d_planet": 52.5,
          "d_ring": 165.0,
          "sigma_p": 27.196000000000005,
          "sigma_r": 18.55516,
          "sigma_lim_p": 33.60183205301333,
          "sigma_lim_r": 19,
          "sf_p": 2.4710863401245278,
          "sf_r": 2.047947848469105,
          "sigma_h": 21.86286016628622,
          "sigma_h_lim_p": 66.52722896214289,
          "sigma_h_lim_r": 29,
          "sh_p": 3.042933470558974,
          "sh_r": 1.3264504177143142,
          "r_eq": 13.167775518038242,
          "temp_flank": {
            "planet": 40.49646480568036,
            "ring": 29.930693347261933
          },
          "temp_root": {
            "planet": 28.698489600289047,
            "ring": 26.176792145546514
          },
          "Pvzp_W": 0.060233458655217224,
          "CoF": 0.12
        },
        "deflection": {
          "lambda_sun_planet_mm": 0.1,
          "lambda_planet_ring_mm": 0.10882352941176471,
          "limit_mm": 0.17500000000000002,
          "ok": true
        },
        "b_over_m": 3.2
      },
      {
        "stage": 3,
        "i": 3.0,
        "n_planets": 4,
        "sun_torque": 60.0,
        "sun_speed_rel": 3.8095238095238093,
        "sp": {
          "SF": [
            4.253190407174422,
            3.7663628029251837
          ],
          "SH": [
            2.3399051295737334,
            2.274264011399162
          ],
          "SigmaF": [
            15.970213041720537,
            17.559092023441803
          ],
          "SigmaH": 28.72808102859236,
          "SH_pess": 2.274264011399162,
          "temps": {
            "flank": [
              36.07033125315333,
              47.140662506306654
            ],
            "root": [
              27.64211905908593,
              30.284238118171857
            ]
          },
          "wear": {
            "NL_ref": 1000000.0,
            "W_mean_mm": [
              0.005621842446050887,
              0.005964110766311609
            ],
            "W_limit_mm": 0.55,
            "N_to_limit": [
              97832695.46914329,
              92218273.86350457
            ],
            "kw_mm3_per_Nm": 1.5e-06,
            "Hv": 0.1806503336430898
          },
          "mats": [
            "PA6_CAST",
            "PA6_CAST"
          ]
        },
        "pr": {
          "force_n": 303.030303030303,
          "d_planet": 49.5,
          "d_ring": 198.0,
          "sigma_p": 22.727272727272727,
          "sigma_r": 14.59752066115702,
          "sigma_lim_p": 33.68567802271302,
          "sigma_lim_r": 19,
          "sf_p": 2.9643396659987458,
          "sf_r": 2.60318179244749,
          "sigma_h": 22.07838791841611,
          "sigma_h_lim_p": 66.69640645065874,
          "sigma_h_lim_r": 29,
          "sh_p": 3.0208911401101743,
          "sh_r": 1.3135016970967528,
          "r_eq": 11.286664729747068,
          "temp_flank": {
            "planet": 39.46291383241277,
            "ring": 28.61572845810319
          },
          "temp_root": {
            "planet": 28.451815434669182,
            "ring": 25.862953858667296
          },
          "Pvzp_W": 0.08460324961649109,
          "CoF": 0.12
        },
        "deflection": {
          "lambda_sun_planet_mm": 0.0874125874125874,
          "lambda_planet_ring_mm": 0.09512546277252158,
          "limit_mm": 0.1925,
          "ok": true
        },
        "b_over_m": 9.454545454545455
      }
    ]
  }
}