{
  "spec_hash": "2ec172d507c63aa9",
  "meta": {
    "name": "N_R24_XM",
    "description": "PA6 i=24 (6x4) подтяжка N_R24_X: b1=35 b2=50. Ø=156 Lax=115."
  },
  "stages": [
    {
      "m": 1.25,
      "b": 35.0,
      "z_sun": 18,
      "z_planet": 36,
      "z_ring": 90,
      "n_planets": 3,
      "x_sun": 0.0,
      "x_planet": 0.0,
      "x_ring": 0.0,
      "mat_sun": "PA6_PRINT",
      "mat_planet": "PA6_PRINT",
      "mat_ring": "PA6_PRINT",
      "n_planets_max": 3,
      "planet_clearance_at_max_mm": 10.957,
      "n_planets_auto": false
    },
    {
      "m": 2.0,
      "b": 50.0,
      "z_sun": 24,
      "z_planet": 24,
      "z_ring": 72,
      "n_planets": 4,
      "x_sun": 0.0,
      "x_planet": 0.0,
      "x_ring": 0.0,
      "mat_sun": "PA6_PRINT",
      "mat_planet": "PA6_PRINT",
      "mat_ring": "PA6_PRINT",
      "n_planets_max": 4,
      "planet_clearance_at_max_mm": 15.882,
      "n_planets_auto": false
    }
  ],
  "load": {
    "mode": "motor",
    "n_in": 150.0,
    "T_in": 3.3
  },
  "cfg": {
    "Ka": 1.3,
    "T_amb": 25.0,
    "eta_stage": 0.9,
    "n_in_ref": 150.0,
    "alpha_deg": 20.0,
    "lubrication": "grease",
    "cycles": 10000000.0
  },
  "raw": {
    "i": [
      6.0,
      4.0
    ],
    "i_total": 24.0,
    "n_stages": 2,
    "t_out": 64.152,
    "n_out": 6.25,
    "T_in_equiv": 3.3,
    "geometry": {
      "valid": true,
      "errors": [],
      "warnings": []
    },
    "model_warnings": [
      "ст.1: b/m = 28.0 > 12 — упрощение K=KA·KV·KHβ·KHα≈1…1.25 (VDI 2736) вне области применимости: широкое колесо работает не всей шириной (перекос/прогиб валов) — реальные SF/SH ниже расчётных; предпочесть крупнее модуль вместо ширины либо поднять Ka",
      "ст.2: b/m = 25.0 > 12 — упрощение K=KA·KV·KHβ·KHα≈1…1.25 (VDI 2736) вне области применимости: широкое колесо работает не всей шириной (перекос/прогиб валов) — реальные SF/SH ниже расчётных; предпочесть крупнее модуль вместо ширины либо поднять Ka",
      "консистентная смазка + полиамид при низком PV (мин ≈ 0.4 МПа·м/с в ст.2, <10) — смазка может НЕ снижать (для PA даже увеличивать) износ; проверить испытанием либо рассмотреть масло/сухой ход"
    ],
    "stages": [
      {
        "stage": 1,
        "i": 6.0,
        "n_planets": 3,
        "sun_torque": 3.3,
        "sun_speed_rel": 125.0,
        "sp": {
          "SF": [
            3.4559371551413256,
            3.7997688807174845
          ],
          "SH": [
            1.353872593413113,
            1.353872593413113
          ],
          "SigmaF": [
            9.259427635249173,
            8.421564838427136
          ],
          "SigmaH": 18.465548473047228,
          "SH_pess": 1.353872593413113,
          "temps": {
            "flank": [
              40.84515072962219,
              32.922575364811095
            ],
            "root": [
              28.78170930746983,
              26.890854653734912
            ]
          },
          "wear": {
            "NL_ref": 1000000.0,
            "W_mean_mm": [
              0.0014295689501574345,
              0.0013475288636400832
            ],
            "W_limit_mm": 0.25,
            "N_to_limit": [
              174877888.87165475,
              185524782.99030593
            ],
            "kw_mm3_per_Nm": 1.5e-06,
            "Hv": 0.18065033364308988
          },
          "mats": [
            "PA6_PRINT",
            "PA6_PRINT"
          ]
        },
        "pr": {
          "force_n": 97.77777777777777,
          "d_planet": 45.0,
          "d_ring": 112.5,
          "sigma_p": 10.009092063492066,
          "sigma_r": 7.538415238095238,
          "sigma_lim_p": 16,
          "sigma_lim_r": 16,
          "sf_p": 3.1970931825793936,
          "sf_r": 4.244924031020288,
          "sigma_h": 9.254211124981259,
          "sigma_h_lim_p": 25,
          "sigma_h_lim_r": 25,
          "sh_p": 2.7014728389450515,
          "sh_r": 2.7014728389450515,
          "r_eq": 12.825755374712577,
          "temp_flank": {
            "planet": 27.166645947566803,
            "ring": 25.86665837902672
          },
          "temp_root": {
            "planet": 25.51710616615261,
            "ring": 25.206842466461044
          },
          "Pvzp_W": 0.08524459649992167,
          "CoF": 0.12
        },
        "deflection": {
          "lambda_sun_planet_mm": 0.02793650793650793,
          "lambda_planet_ring_mm": 0.02793650793650793,
          "limit_mm": 0.08750000000000001,
          "ok": true
        },
        "b_over_m": 28.0
      },
      {
        "stage": 2,
        "i": 4.0,
        "n_planets": 4,
        "sun_torque": 17.819999999999997,
        "sun_speed_rel": 18.75,
        "sp": {
          "SF": [
            4.366955985278283,
            4.366955985278283
          ],
          "SH": [
            1.4827081293343303,
            1.4827081293343303
          ],
          "SigmaF": [
            7.32775876557428,
            7.32775876557428
          ],
          "SigmaH": 16.861039273605307,
          "SH_pess": 1.4827081293343303,
          "temps": {
            "flank": [
              33.236662732955516,
              33.236662732955516
            ],
            "root": [
              26.96581683893205,
              26.96581683893205
            ]
          },
          "wear": {
            "NL_ref": 1000000.0,
            "W_mean_mm": [
              0.0018124962864155929,
              0.0018124962864155929
            ],
            "W_limit_mm": 0.4,
            "N_to_limit": [
              220690107.33867115,
              220690107.33867115
            ],
            "kw_mm3_per_Nm": 1.5e-06,
            "Hv": 0.17832296570938455
          },
          "mats": [
            "PA6_PRINT",
            "PA6_PRINT"
          ]
        },
        "pr": {
          "force_n": 185.62499999999997,
          "d_planet": 48.0,
          "d_ring": 144.0,
          "sigma_p": 9.121612499999998,
          "sigma_r": 6.3934540312499974,
          "sigma_lim_p": 16,
          "sigma_lim_r": 16,
          "sf_p": 3.5081516562998054,
          "sf_r": 5.005119274118503,
          "sigma_h": 10.888071363813877,
          "sigma_h_lim_p": 25,
          "sigma_h_lim_r": 25,
          "sh_p": 2.2960907551622616,
          "sh_r": 2.2960907551622616,
          "r_eq": 12.312725159724073,
          "temp_flank": {
            "planet": 28.768241031548946,
            "ring": 26.25608034384965
          },
          "temp_root": {
            "planet": 25.89935352619635,
            "ring": 25.299784508732117
          },
          "Pvzp_W": 0.08546351609520761,
          "CoF": 0.12
        },
        "deflection": {
          "lambda_sun_planet_mm": 0.03712499999999999,
          "lambda_planet_ring_mm": 0.03712499999999999,
          "limit_mm": 0.14,
          "ok": true
        },
        "b_over_m": 25.0
      }
    ]
  }
}