{
  "spec_hash": "7aca5eb53dfc2e19",
  "meta": {
    "name": "thigh180-CAP-ALL-D134",
    "description": null
  },
  "stages": [
    {
      "m": 1.0,
      "b": 10.0,
      "z_sun": 18,
      "z_planet": 45,
      "z_ring": 108,
      "n_planets": 3,
      "x_sun": 0.0,
      "x_planet": 0.0,
      "x_ring": 0.0,
      "mat_sun": "PA6_CAST",
      "mat_planet": "PA6_CAST",
      "mat_ring": "PA6_CAST",
      "n_planets_max": 3,
      "planet_clearance_at_max_mm": 7.56,
      "n_planets_auto": true
    },
    {
      "m": 1.75,
      "b": 12.0,
      "z_sun": 24,
      "z_planet": 21,
      "z_ring": 66,
      "n_planets": 5,
      "x_sun": 0.0,
      "x_planet": 0.0,
      "x_ring": 0.0,
      "mat_sun": "PA6_CAST",
      "mat_planet": "PA6_CAST",
      "mat_ring": "PA6_CAST",
      "n_planets_max": 5,
      "planet_clearance_at_max_mm": 6.038,
      "n_planets_auto": true
    },
    {
      "m": 1.75,
      "b": 25.0,
      "z_sun": 36,
      "z_planet": 18,
      "z_ring": 72,
      "n_planets": 6,
      "x_sun": 0.0,
      "x_planet": 0.0,
      "x_ring": 0.0,
      "mat_sun": "PA6_CAST",
      "mat_planet": "PA6_CAST",
      "mat_ring": "PA6_CAST",
      "n_planets_max": 6,
      "planet_clearance_at_max_mm": 12.25,
      "n_planets_auto": true
    }
  ],
  "load": {
    "mode": "output",
    "n_in": 150.0,
    "T_out_req": 180.0
  },
  "cfg": {
    "Ka": 1.3,
    "T_amb": 25.0,
    "eta_stage": 0.9,
    "n_in_ref": 150.0,
    "alpha_deg": 20.0,
    "lubrication": "grease",
    "cycles": 10000000.0
  },
  "raw": {
    "i": [
      7.0,
      3.75,
      3.0
    ],
    "i_total": 78.75,
    "n_stages": 3,
    "t_out": 180.0,
    "n_out": 1.9047619047619047,
    "T_in_equiv": 2.2857142857142856,
    "geometry": {
      "valid": true,
      "errors": [],
      "warnings": []
    },
    "model_warnings": [
      "ст.3: b/m = 14.3 > 12 — упрощение K=KA·KV·KHβ·KHα≈1…1.25 (VDI 2736) вне области применимости: широкое колесо работает не всей шириной (перекос/прогиб валов) — реальные SF/SH ниже расчётных; предпочесть крупнее модуль вместо ширины либо поднять Ka",
      "консистентная смазка + полиамид при низком PV (мин ≈ 0.3 МПа·м/с в ст.3, <10) — смазка может НЕ снижать (для PA даже увеличивать) износ; проверить испытанием либо рассмотреть масло/сухой ход"
    ],
    "stages": [
      {
        "stage": 1,
        "i": 7.0,
        "n_planets": 3,
        "sun_torque": 2.2857142857142856,
        "sun_speed_rel": 128.57142857142858,
        "sp": {
          "SF": [
            1.7700270623163274,
            2.126274068746709
          ],
          "SH": [
            1.4824912161793902,
            1.680646757733927
          ],
          "SigmaF": [
            34.7703095424937,
            31.217531444599803
          ],
          "SigmaH": 39.04653206144038,
          "SH_pess": 1.4824912161793902,
          "temps": {
            "flank": [
              76.55768123426928,
              45.62307249370771
            ],
            "root": [
              37.3050999212456,
              29.92203996849824
            ]
          },
          "wear": {
            "NL_ref": 1000000.0,
            "W_mean_mm": [
              0.004123744404310197,
              0.0038440113022935145
            ],
            "W_limit_mm": 0.2,
            "N_to_limit": [
              48499611.127924696,
              52028983.33849091
            ],
            "kw_mm3_per_Nm": 1.5e-06,
            "Hv": 0.17239380711786625
          },
          "mats": [
            "PA6_CAST",
            "PA6_CAST"
          ]
        },
        "pr": {
          "force_n": 84.65608465608466,
          "d_planet": 45.0,
          "d_ring": 108.0,
          "sigma_p": 36.400000000000006,
          "sigma_r": 28.23187301587302,
          "sigma_lim_p": 34.49498663034345,
          "sigma_lim_r": 34.71857286161982,
          "sf_p": 1.8953289357331562,
          "sf_r": 2.4595302509401153,
          "sigma_h": 17.945297141756456,
          "sigma_h_lim_p": 68.09042192719818,
          "sigma_h_lim_r": 68.40111933405456,
          "sh_p": 3.7943323751803644,
          "sh_r": 3.8116459590347898,
          "r_eq": 13.192205528275792,
          "temp_flank": {
            "planet": 29.60327938436823,
            "ring": 26.918033076820095
          },
          "temp_root": {
            "planet": 26.09864934640255,
            "ring": 25.457770561001063
          },
          "Pvzp_W": 0.04727146219582435,
          "CoF": 0.12
        },
        "deflection": {
          "lambda_sun_planet_mm": 0.06349206349206349,
          "lambda_planet_ring_mm": 0.06349206349206349,
          "limit_mm": 0.07,
          "ok": true
        },
        "b_over_m": 10.0
      },
      {
        "stage": 2,
        "i": 3.75,
        "n_planets": 5,
        "sun_torque": 16.0,
        "sun_speed_rel": 15.714285714285714,
        "sp": {
          "SF": [
            2.247524364155995,
            2.1767068276924886
          ],
          "SH": [
            1.625591832569033,
            1.5993460281879417
          ],
          "SigmaF": [
            28.83780991668649,
            29.46220593318809
          ],
          "SigmaH": 39.11718367725942,
          "SH_pess": 1.5993460281879417,
          "temps": {
            "flank": [
              55.45698506068531,
              59.8079829264975
            ],
            "root": [
              32.26906710115023,
              33.307505258457404
            ]
          },
          "wear": {
            "NL_ref": 1000000.0,
            "W_mean_mm": [
              0.006577729167361143,
              0.006661357640479549
            ],
            "W_limit_mm": 0.35000000000000003,
            "N_to_limit": [
              53209852.68543874,
              52541841.90218672
            ],
            "kw_mm3_per_Nm": 1.5e-06,
            "Hv": 0.18836910494252546
          },
          "mats": [
            "PA6_CAST",
            "PA6_CAST"
          ]
        },
        "pr": {
          "force_n": 152.38095238095238,
          "d_planet": 36.75,
          "d_ring": 115.5,
          "sigma_p": 37.0013605442177,
          "sigma_r": 25.245115646258505,
          "sigma_lim_p": 33.42851616510422,
          "sigma_lim_r": 34.411307038270714,
          "sf_p": 1.8068803780961609,
          "sf_r": 2.726175432939298,
          "sigma_h": 26.293582375895046,
          "sigma_h_lim_p": 66.16245198121322,
          "sigma_h_lim_r": 67.96599539373474,
          "sh_p": 2.5162966017847928,
          "sh_r": 2.5848891346218146,
          "r_eq": 9.217442862626772,
          "temp_flank": {
            "planet": 42.639826742183516,
            "ring": 30.61267214524021
          },
          "temp_root": {
            "planet": 29.210038649134468,
            "ring": 26.33955775199733
          },
          "Pvzp_W": 0.06023345865521717,
          "CoF": 0.12
        },
        "deflection": {
          "lambda_sun_planet_mm": 0.09523809523809525,
          "lambda_planet_ring_mm": 0.09523809523809525,
          "limit_mm": 0.12250000000000001,
          "ok": true
        },
        "b_over_m": 6.857142857142857
      },
      {
        "stage": 3,
        "i": 3.0,
        "n_planets": 6,
        "sun_torque": 60.0,
        "sun_speed_rel": 3.8095238095238093,
        "sp": {
          "SF": [
            2.460058371918604,
            2.1570632267029803
          ],
          "SH": [
            1.771465857761564,
            1.6929465473348746
          ],
          "SigmaF": [
            27.342742981906287,
            30.063076737821984
          ],
          "SigmaH": 37.58999797590951,
          "SH_pess": 1.6929465473348746,
          "temps": {
            "flank": [
              40.119751878026435,
              55.239503756052876
            ],
            "root": [
              28.608580781555645,
              32.21716156311129
            ]
          },
          "wear": {
            "NL_ref": 1000000.0,
            "W_mean_mm": [
              0.006125131198364018,
              0.0064980406825337934
            ],
            "W_limit_mm": 0.35000000000000003,
            "N_to_limit": [
              57141633.16101421,
              53862389.77246967
            ],
            "kw_mm3_per_Nm": 1.5e-06,
            "Hv": 0.18065033364308988
          },
          "mats": [
            "PA6_CAST",
            "PA6_CAST"
          ]
        },
        "pr": {
          "force_n": 317.46031746031747,
          "d_planet": 31.5,
          "d_ring": 126.0,
          "sigma_p": 38.911564625850346,
          "sigma_r": 24.992544217687072,
          "sigma_lim_p": 33.25834166516185,
          "sigma_lim_r": 34.467188964968294,
          "sf_p": 1.7094322464261509,
          "sf_r": 2.758197698061974,
          "sigma_h": 29.786501559756992,
          "sigma_h_lim_p": 65.78434291675345,
          "sigma_h_lim_r": 68.04958354694278,
          "sh_p": 2.2085286781590785,
          "sh_r": 2.284577912260803,
          "r_eq": 7.182423009839043,
          "temp_flank": {
            "planet": 44.75330851252248,
            "ring": 29.93832712813062
          },
          "temp_root": {
            "planet": 29.714456298322034,
            "ring": 26.17861407458051
          },
          "Pvzp_W": 0.05640216641099401,
          "CoF": 0.12
        },
        "deflection": {
          "lambda_sun_planet_mm": 0.09523809523809525,
          "lambda_planet_ring_mm": 0.09523809523809525,
          "limit_mm": 0.12250000000000001,
          "ok": true
        },
        "b_over_m": 14.285714285714286
      }
    ]
  }
}