{
  "spec_hash": "7bb782c8b91d26bc",
  "meta": {
    "name": "Y_R32_I",
    "description": "POM i=32 (8x4) Ø180 широкий: m1=1.25 Z18-54-126 b1=30, m2=2.5 Z22-22-66 b2=40. Ø=180 Lax=100."
  },
  "stages": [
    {
      "m": 1.25,
      "b": 30.0,
      "z_sun": 18,
      "z_planet": 54,
      "z_ring": 126,
      "n_planets": 3,
      "x_sun": 0.0,
      "x_planet": 0.0,
      "x_ring": 0.0,
      "mat_sun": "POM_C",
      "mat_planet": "POM_C",
      "mat_ring": "PETG",
      "n_planets_max": 3,
      "planet_clearance_at_max_mm": 7.942,
      "n_planets_auto": false
    },
    {
      "m": 2.5,
      "b": 40.0,
      "z_sun": 22,
      "z_planet": 22,
      "z_ring": 66,
      "n_planets": 4,
      "x_sun": 0.0,
      "x_planet": 0.0,
      "x_ring": 0.0,
      "mat_sun": "POM_C",
      "mat_planet": "POM_C",
      "mat_ring": "PETG",
      "n_planets_max": 4,
      "planet_clearance_at_max_mm": 17.782,
      "n_planets_auto": false
    }
  ],
  "load": {
    "mode": "motor",
    "n_in": 150.0,
    "T_in": 3.3
  },
  "cfg": {
    "Ka": 1.3,
    "T_amb": 25.0,
    "eta_stage": 0.9,
    "n_in_ref": 150.0,
    "alpha_deg": 20.0,
    "lubrication": "grease",
    "cycles": 10000000.0
  },
  "raw": {
    "i": [
      8.0,
      4.0
    ],
    "i_total": 32.0,
    "n_stages": 2,
    "t_out": 85.536,
    "n_out": 4.6875,
    "T_in_equiv": 3.3,
    "geometry": {
      "valid": true,
      "errors": [],
      "warnings": []
    },
    "model_warnings": [
      "ст.1: b/m = 24.0 > 12 — упрощение K=KA·KV·KHβ·KHα≈1…1.25 (VDI 2736) вне области применимости: широкое колесо работает не всей шириной (перекос/прогиб валов) — реальные SF/SH ниже расчётных; предпочесть крупнее модуль вместо ширины либо поднять Ka",
      "ст.2: b/m = 16.0 > 12 — упрощение K=KA·KV·KHβ·KHα≈1…1.25 (VDI 2736) вне области применимости: широкое колесо работает не всей шириной (перекос/прогиб валов) — реальные SF/SH ниже расчётных; предпочесть крупнее модуль вместо ширины либо поднять Ka"
    ],
    "stages": [
      {
        "stage": 1,
        "i": 8.0,
        "n_planets": 3,
        "sun_torque": 3.3,
        "sun_speed_rel": 131.25,
        "sp": {
          "SF": [
            4.886218225298268,
            5.478255871156032
          ],
          "SH": [
            1.3558982880711847,
            1.3558982880711847
          ],
          "SigmaF": [
            10.642177160809426,
            9.492072152706307
          ],
          "SigmaH": 25.81314565253179,
          "SH_pess": 1.3558982880711847,
          "temps": {
            "flank": [
              42.284242846664306,
              30.761414282221434
            ],
            "root": [
              29.125172626070547,
              26.375057542023516
            ]
          },
          "wear": {
            "NL_ref": 1000000.0,
            "W_mean_mm": [
              0.0009211267465747789,
              0.0008523573318009214
            ],
            "W_limit_mm": 0.25,
            "N_to_limit": [
              271406731.95043796,
              293304217.2251656
            ],
            "kw_mm3_per_Nm": 9e-07,
            "Hv": 0.16697466380990675
          },
          "mats": [
            "POM_C",
            "POM_C"
          ]
        },
        "pr": {
          "force_n": 97.77777777777777,
          "d_planet": 67.5,
          "d_ring": 157.5,
          "sigma_p": 10.901048888888889,
          "sigma_r": 8.617624888888887,
          "sigma_lim_p": 26,
          "sigma_lim_r": 12,
          "sf_p": 4.770183175033921,
          "sf_r": 2.7849900998759343,
          "sigma_h": 9.985943304153938,
          "sigma_h_lim_p": 35,
          "sigma_h_lim_r": 22,
          "sh_p": 3.5049267689553925,
          "sh_r": 2.2030968262005324,
          "r_eq": 20.200564715172305,
          "temp_flank": {
            "planet": 26.086165123149556,
            "ring": 25.465499338492666
          },
          "temp_root": {
            "planet": 25.259231409391695,
            "ring": 25.11109917545358
          },
          "Pvzp_W": 0.056991646982207926,
          "CoF": 0.12
        },
        "deflection": {
          "lambda_sun_planet_mm": 0.016296296296296295,
          "lambda_planet_ring_mm": 0.02037037037037037,
          "limit_mm": 0.08750000000000001,
          "ok": true
        },
        "b_over_m": 24.0
      },
      {
        "stage": 2,
        "i": 4.0,
        "n_planets": 4,
        "sun_torque": 23.759999999999998,
        "sun_speed_rel": 14.0625,
        "sp": {
          "SF": [
            5.964672971554399,
            5.964672971554399
          ],
          "SH": [
            1.3256775955958628,
            1.3256775955958628
          ],
          "SigmaF": [
            8.717996820276428,
            8.717996820276428
          ],
          "SigmaH": 26.401592752473327,
          "SH_pess": 1.3256775955958628,
          "temps": {
            "flank": [
              36.39448832462186,
              36.39448832462186
            ],
            "root": [
              27.719484546809753,
              27.719484546809753
            ]
          },
          "wear": {
            "NL_ref": 1000000.0,
            "W_mean_mm": [
              0.0017165734817358635,
              0.0017165734817358633
            ],
            "W_limit_mm": 0.5,
            "N_to_limit": [
              291277947.21282846,
              291277947.21282846
            ],
            "kw_mm3_per_Nm": 9e-07,
            "Hv": 0.19095293287872517
          },
          "mats": [
            "POM_C",
            "POM_C"
          ]
        },
        "pr": {
          "force_n": 215.99999999999997,
          "d_planet": 55.0,
          "d_ring": 165.0,
          "sigma_p": 10.866959999999999,
          "sigma_r": 7.514839799999997,
          "sigma_lim_p": 26,
          "sigma_lim_r": 12,
          "sf_p": 4.785146904009953,
          "sf_r": 3.193680855312446,
          "sigma_h": 15.38050015398904,
          "sigma_h_lim_p": 35,
          "sigma_h_lim_r": 22,
          "sh_p": 2.2756087025507106,
          "sh_r": 1.430382613031875,
          "r_eq": 14.108330912183833,
          "temp_flank": {
            "planet": 30.352069721776076,
            "ring": 26.784023240592028
          },
          "temp_root": {
            "planet": 26.27736064026389,
            "ring": 25.425786880087962
          },
          "Pvzp_W": 0.09392578145381039,
          "CoF": 0.12
        },
        "deflection": {
          "lambda_sun_planet_mm": 0.026999999999999993,
          "lambda_planet_ring_mm": 0.033749999999999995,
          "limit_mm": 0.17500000000000002,
          "ok": true
        },
        "b_over_m": 16.0
      }
    ]
  }
}