{
  "spec_hash": "a0d2b91130a693ee",
  "meta": {
    "name": "N_R42_A40",
    "description": "PA6 i=42 (7x6) шире ст.2: m1=1.25 Z18-45-108 b1=28, m2=1.25 Z24-48-120 b2=40. Ø=157.5 Lax=98."
  },
  "stages": [
    {
      "m": 1.25,
      "b": 28.0,
      "z_sun": 18,
      "z_planet": 45,
      "z_ring": 108,
      "n_planets": 3,
      "x_sun": 0.0,
      "x_planet": 0.0,
      "x_ring": 0.0,
      "mat_sun": "PA6_PRINT",
      "mat_planet": "PA6_PRINT",
      "mat_ring": "PA6_PRINT",
      "n_planets_max": 3,
      "planet_clearance_at_max_mm": 9.45,
      "n_planets_auto": false
    },
    {
      "m": 1.25,
      "b": 40.0,
      "z_sun": 24,
      "z_planet": 48,
      "z_ring": 120,
      "n_planets": 4,
      "x_sun": 0.0,
      "x_planet": 0.0,
      "x_ring": 0.0,
      "mat_sun": "PA6_PRINT",
      "mat_planet": "PA6_PRINT",
      "mat_ring": "PA6_PRINT",
      "n_planets_max": 3,
      "planet_clearance_at_max_mm": 15.442,
      "n_planets_auto": false
    }
  ],
  "load": {
    "mode": "motor",
    "n_in": 150.0,
    "T_in": 3.3
  },
  "cfg": {
    "Ka": 1.3,
    "T_amb": 25.0,
    "eta_stage": 0.9,
    "n_in_ref": 150.0,
    "alpha_deg": 20.0,
    "lubrication": "grease",
    "cycles": 10000000.0
  },
  "raw": {
    "i": [
      7.0,
      6.0
    ],
    "i_total": 42.0,
    "n_stages": 2,
    "t_out": 112.266,
    "n_out": 3.5714285714285716,
    "T_in_equiv": 3.3,
    "geometry": {
      "valid": true,
      "errors": [],
      "warnings": [
        "ст.2: СОСЕДСТВО: зазор 1.14 мм мал (<1.5 мм) для 4 саттелитов — туго для FFF-печати"
      ]
    },
    "model_warnings": [
      "ст.1: b/m = 22.4 > 12 — упрощение K=KA·KV·KHβ·KHα≈1…1.25 (VDI 2736) вне области применимости: широкое колесо работает не всей шириной (перекос/прогиб валов) — реальные SF/SH ниже расчётных; предпочесть крупнее модуль вместо ширины либо поднять Ka",
      "ст.2: b/m = 32.0 > 12 — упрощение K=KA·KV·KHβ·KHα≈1…1.25 (VDI 2736) вне области применимости: широкое колесо работает не всей шириной (перекос/прогиб валов) — реальные SF/SH ниже расчётных; предпочесть крупнее модуль вместо ширины либо поднять Ka",
      "консистентная смазка + полиамид при низком PV (мин ≈ 0.3 МПа·м/с в ст.2, <10) — смазка может НЕ снижать (для PA даже увеличивать) износ; проверить испытанием либо рассмотреть масло/сухой ход"
    ],
    "stages": [
      {
        "stage": 1,
        "i": 7.0,
        "n_planets": 3,
        "sun_torque": 3.3,
        "sun_speed_rel": 128.57142857142858,
        "sp": {
          "SF": [
            2.788864932340847,
            3.1062576854221886
          ],
          "SH": [
            1.25917478883466,
            1.25917478883466
          ],
          "SigmaF": [
            11.474202149022917,
            10.301785376717934
          ],
          "SigmaH": 19.854272990278798,
          "SH_pess": 1.25917478883466,
          "temps": {
            "flank": [
              44.02226920034507,
              32.60890768013803
            ],
            "root": [
              29.539981582482355,
              26.815992632992945
            ]
          },
          "wear": {
            "NL_ref": 1000000.0,
            "W_mean_mm": [
              0.0017010445667779562,
              0.0015856546621960748
            ],
            "W_limit_mm": 0.25,
            "N_to_limit": [
              146968518.56946877,
              157663585.87421486
            ],
            "kw_mm3_per_Nm": 1.5e-06,
            "Hv": 0.17239380711786628
          },
          "mats": [
            "PA6_PRINT",
            "PA6_PRINT"
          ]
        },
        "pr": {
          "force_n": 97.77777777777777,
          "d_planet": 56.25,
          "d_ring": 135.0,
          "sigma_p": 12.012,
          "sigma_r": 9.316518095238095,
          "sigma_lim_p": 16,
          "sigma_lim_r": 16,
          "sf_p": 2.664002664002664,
          "sf_r": 3.4347596036287418,
          "sigma_h": 9.124775224172863,
          "sigma_h_lim_p": 25,
          "sigma_h_lim_r": 25,
          "sh_p": 2.739793516641522,
          "sh_r": 2.739793516641522,
          "r_eq": 16.49025691034474,
          "temp_flank": {
            "planet": 26.698385527773677,
            "ring": 25.707660636572363
          },
          "temp_root": {
            "planet": 25.40534801262865,
            "ring": 25.168895005261938
          },
          "Pvzp_W": 0.06824817354522156,
          "CoF": 0.12
        },
        "deflection": {
          "lambda_sun_planet_mm": 0.034920634920634915,
          "lambda_planet_ring_mm": 0.034920634920634915,
          "limit_mm": 0.08750000000000001,
          "ok": true
        },
        "b_over_m": 22.4
      },
      {
        "stage": 2,
        "i": 6.0,
        "n_planets": 4,
        "sun_torque": 20.79,
        "sun_speed_rel": 17.857142857142854,
        "sp": {
          "SF": [
            1.2038363161834627,
            1.2762583906736142
          ],
          "SH": [
            0.899851861179585,
            0.899851861179585
          ],
          "SigmaF": [
            26.581686870396137,
            25.073292550978078
          ],
          "SigmaH": 27.78235071629274,
          "SH_pess": 0.899851861179585,
          "temps": {
            "flank": [
              44.31345823819586,
              34.65672911909793
            ],
            "root": [
              29.609478699516078,
              27.304739349758037
            ]
          },
          "wear": {
            "NL_ref": 1000000.0,
            "W_mean_mm": [
              0.0033402318177455483,
              0.003210741669053521
            ],
            "W_limit_mm": 0.25,
            "N_to_limit": [
              74845104.66364418,
              77863629.58116661
            ],
            "kw_mm3_per_Nm": 1.5e-06,
            "Hv": 0.1433869228777667
          },
          "mats": [
            "PA6_PRINT",
            "PA6_PRINT"
          ]
        },
        "pr": {
          "force_n": 346.5,
          "d_planet": 60.0,
          "d_ring": 150.0,
          "sigma_p": 29.432403,
          "sigma_r": 22.97295,
          "sigma_lim_p": 16,
          "sigma_lim_r": 16,
          "sf_p": 1.0872370835639888,
          "sf_r": 1.3929425694131576,
          "sigma_h": 14.112553442927553,
          "sigma_h_lim_p": 25,
          "sigma_h_lim_r": 25,
          "sh_p": 1.7714724766926317,
          "sh_r": 1.7714724766926317,
          "r_eq": 17.101007166283434,
          "temp_flank": {
            "planet": 27.488610969924014,
            "ring": 25.995444387969606
          },
          "temp_root": {
            "planet": 25.593948484821865,
            "ring": 25.237579393928748
          },
          "Pvzp_W": 0.043017694175492685,
          "CoF": 0.12
        },
        "deflection": {
          "lambda_sun_planet_mm": 0.086625,
          "lambda_planet_ring_mm": 0.086625,
          "limit_mm": 0.08750000000000001,
          "ok": true
        },
        "b_over_m": 32.0
      }
    ]
  }
}