{
  "spec_hash": "ca9d6af3ca0bb716",
  "meta": {
    "name": "V24A",
    "description": "V24 + m1=1.5, b1=30. Ст.2 та же."
  },
  "stages": [
    {
      "m": 1.5,
      "b": 30.0,
      "z_sun": 18,
      "z_planet": 36,
      "z_ring": 90,
      "n_planets": 3,
      "x_sun": 0.0,
      "x_planet": 0.0,
      "x_ring": 0.0,
      "mat_sun": "PA6_CF",
      "mat_planet": "PA6_CF",
      "mat_ring": "PA6_CF",
      "n_planets_max": 3,
      "planet_clearance_at_max_mm": 13.148,
      "n_planets_auto": false
    },
    {
      "m": 2.0,
      "b": 30.0,
      "z_sun": 18,
      "z_planet": 18,
      "z_ring": 54,
      "n_planets": 4,
      "x_sun": 0.0,
      "x_planet": 0.0,
      "x_ring": 0.0,
      "mat_sun": "D16T",
      "mat_planet": "PA6_CF",
      "mat_ring": "PA6_CF",
      "n_planets_max": 4,
      "planet_clearance_at_max_mm": 10.912,
      "n_planets_auto": false
    }
  ],
  "load": {
    "mode": "motor",
    "n_in": 150.0,
    "T_in": 3.3
  },
  "cfg": {
    "Ka": 1.3,
    "T_amb": 25.0,
    "eta_stage": 0.9,
    "n_in_ref": 150.0,
    "alpha_deg": 20.0,
    "lubrication": "grease",
    "cycles": 10000000.0
  },
  "raw": {
    "i": [
      6.0,
      4.0
    ],
    "i_total": 24.0,
    "n_stages": 2,
    "t_out": 64.152,
    "n_out": 6.25,
    "T_in_equiv": 3.3,
    "geometry": {
      "valid": true,
      "errors": [],
      "warnings": []
    },
    "model_warnings": [
      "ст.1: b/m = 20.0 > 12 — упрощение K=KA·KV·KHβ·KHα≈1…1.25 (VDI 2736) вне области применимости: широкое колесо работает не всей шириной (перекос/прогиб валов) — реальные SF/SH ниже расчётных; предпочесть крупнее модуль вместо ширины либо поднять Ka",
      "ст.2: b/m = 15.0 > 12 — упрощение K=KA·KV·KHβ·KHα≈1…1.25 (VDI 2736) вне области применимости: широкое колесо работает не всей шириной (перекос/прогиб валов) — реальные SF/SH ниже расчётных; предпочесть крупнее модуль вместо ширины либо поднять Ka",
      "консистентная смазка + полиамид при низком PV (мин ≈ 1.1 МПа·м/с в ст.2, <10) — смазка может НЕ снижать (для PA даже увеличивать) износ; проверить испытанием либо рассмотреть масло/сухой ход"
    ],
    "stages": [
      {
        "stage": 1,
        "i": 6.0,
        "n_planets": 3,
        "sun_torque": 3.3,
        "sun_speed_rel": 125.0,
        "sp": {
          "SF": [
            4.79881559256767,
            5.276250502939136
          ],
          "SH": [
            1.0115855917913723,
            1.0115855917913723
          ],
          "SigmaF": [
            7.501851093373173,
            6.823027068170133
          ],
          "SigmaH": 34.59914839041949,
          "SH_pess": 1.0115855917913723,
          "temps": {
            "flank": [
              39.06278365087607,
              32.031391825438035
            ],
            "root": [
              28.35631769800909,
              26.678158849004543
            ]
          },
          "wear": {
            "NL_ref": 1000000.0,
            "W_mean_mm": [
              0.00027797174030839023,
              0.00026201950126334957
            ],
            "W_limit_mm": 0.30000000000000004,
            "N_to_limit": [
              1079246399.8936403,
              1144952946.4544594
            ],
            "kw_mm3_per_Nm": 3e-07,
            "Hv": 0.18065033364309005
          },
          "mats": [
            "PA6_CF",
            "PA6_CF"
          ]
        },
        "pr": {
          "force_n": 81.48148148148148,
          "d_planet": 54.0,
          "d_ring": 135.0,
          "sigma_p": 8.109218106995884,
          "sigma_r": 6.107512345679013,
          "sigma_lim_p": 18,
          "sigma_lim_r": 18,
          "sf_p": 4.439392247810245,
          "sf_r": 5.894380225931028,
          "sigma_h": 17.33974078359229,
          "sigma_h_lim_p": 35,
          "sigma_h_lim_r": 35,
          "sh_p": 2.018484615013317,
          "sh_r": 2.018484615013317,
          "r_eq": 15.390906449655096,
          "temp_flank": {
            "planet": 26.922927318811677,
            "ring": 25.769170927524673
          },
          "temp_root": {
            "planet": 25.458938653423054,
            "ring": 25.183575461369223
          },
          "Pvzp_W": 0.08524459649992167,
          "CoF": 0.12
        },
        "deflection": {
          "lambda_sun_planet_mm": 0.006267806267806268,
          "lambda_planet_ring_mm": 0.006267806267806268,
          "limit_mm": 0.10500000000000001,
          "ok": true
        },
        "b_over_m": 20.0
      },
      {
        "stage": 2,
        "i": 4.0,
        "n_planets": 4,
        "sun_torque": 17.819999999999997,
        "sun_speed_rel": 18.75,
        "sp": {
          "SF": [
            14.704745241827904,
            2.0360416488684794
          ],
          "SH": [
            2.052103984033411,
            0.4224919967127611
          ],
          "SigmaF": [
            17.681367186180516,
            17.681367186180516
          ],
          "SigmaH": 82.84180593317934,
          "SH_pess": 0.4224919967127611,
          "temps": {
            "flank": [
              38.29395715152358,
              38.29395715152358
            ],
            "root": [
              26.888585976287875,
              26.888585976287875
            ]
          },
          "wear": {
            "NL_ref": 1000000.0,
            "W_mean_mm": [
              0.0010573213242537952,
              0.0010573213242537952
            ],
            "W_limit_mm": 0.4,
            "N_to_limit": [
              378314511.2317678,
              378314511.2317678
            ],
            "kw_mm3_per_Nm": 3e-07,
            "Hv": 0.2235158740299564
          },
          "mats": [
            "D16T",
            "PA6_CF"
          ]
        },
        "pr": {
          "force_n": 247.49999999999994,
          "d_planet": 36.0,
          "d_ring": 108.0,
          "sigma_p": 22.120312499999997,
          "sigma_r": 14.658929999999998,
          "sigma_lim_p": 18,
          "sigma_lim_r": 18,
          "sf_p": 1.6274634456452641,
          "sf_r": 2.45584091062581,
          "sigma_h": 39.01441676308265,
          "sigma_h_lim_p": 35,
          "sigma_h_lim_r": 35,
          "sh_p": 0.8971042733392521,
          "sh_r": 0.8971042733392521,
          "r_eq": 9.234543869793056,
          "temp_flank": {
            "planet": 39.38872678630645,
            "ring": 29.79624226210215
          },
          "temp_root": {
            "planet": 28.434109459665137,
            "ring": 26.144703153221712
          },
          "Pvzp_W": 0.1183512664989695,
          "CoF": 0.12
        },
        "deflection": {
          "lambda_sun_planet_mm": 0.010378605769230767,
          "lambda_planet_ring_mm": 0.019038461538461535,
          "limit_mm": 0.14,
          "ok": true
        },
        "b_over_m": 15.0
      }
    ]
  }
}